{"nodes": [{"id": "d_torus_implementation_project_torus_implementation_torus_implementation_gmail_smtp_setup_md", "label": "GMAIL-SMTP-SETUP.md", "file_type": "document", "source_file": "GMAIL-SMTP-SETUP.md", "source_location": "L1"}, {"id": "torus_implementation_gmail_smtp_setup_gmail_smtp_otp_system_successfully_configured", "label": "\u2705 Gmail SMTP OTP System - Successfully Configured", "file_type": "document", "source_file": "GMAIL-SMTP-SETUP.md", "source_location": "L1"}, {"id": "torus_implementation_gmail_smtp_setup_status_fully_operational", "label": "\ud83c\udf89 Status: FULLY OPERATIONAL", "file_type": "document", "source_file": "GMAIL-SMTP-SETUP.md", "source_location": "L3"}, {"id": "torus_implementation_gmail_smtp_setup_what_changed", "label": "\ud83d\udcca What Changed", "file_type": "document", "source_file": "GMAIL-SMTP-SETUP.md", "source_location": "L11"}, {"id": "torus_implementation_gmail_smtp_setup_from_resend_api", "label": "**From: Resend API**", "file_type": "document", "source_file": "GMAIL-SMTP-SETUP.md", "source_location": "L13"}, {"id": "torus_implementation_gmail_smtp_setup_to_gmail_smtp_nodemailer", "label": "**To: Gmail SMTP (Nodemailer)**", "file_type": "document", "source_file": "GMAIL-SMTP-SETUP.md", "source_location": "L21"}, {"id": "torus_implementation_gmail_smtp_setup_configuration", "label": "\ud83d\udd27 Configuration", "file_type": "document", "source_file": "GMAIL-SMTP-SETUP.md", "source_location": "L31"}, {"id": "torus_implementation_gmail_smtp_setup_installed_dependency", "label": "**Installed Dependency**", "file_type": "document", "source_file": "GMAIL-SMTP-SETUP.md", "source_location": "L33"}, {"id": "torus_implementation_gmail_smtp_setup_updated_env", "label": "**Updated .env**", "file_type": "document", "source_file": "GMAIL-SMTP-SETUP.md", "source_location": "L39"}, {"id": "torus_implementation_gmail_smtp_setup_backend_configuration_server_js", "label": "**Backend Configuration (server.js)**", "file_type": "document", "source_file": "GMAIL-SMTP-SETUP.md", "source_location": "L49"}, {"id": "torus_implementation_gmail_smtp_setup_send_otp_function", "label": "\ud83d\udce7 Send OTP Function", "file_type": "document", "source_file": "GMAIL-SMTP-SETUP.md", "source_location": "L70"}, {"id": "torus_implementation_gmail_smtp_setup_test_results", "label": "\ud83e\uddea Test Results", "file_type": "document", "source_file": "GMAIL-SMTP-SETUP.md", "source_location": "L102"}, {"id": "torus_implementation_gmail_smtp_setup_test_1_otp_sending", "label": "**Test 1: OTP Sending \u2705**", "file_type": "document", "source_file": "GMAIL-SMTP-SETUP.md", "source_location": "L104"}, {"id": "torus_implementation_gmail_smtp_setup_how_to_use", "label": "\ud83c\udfaf How to Use", "file_type": "document", "source_file": "GMAIL-SMTP-SETUP.md", "source_location": "L121"}, {"id": "torus_implementation_gmail_smtp_setup_1_get_gmail_app_password", "label": "**1. Get Gmail App Password**", "file_type": "document", "source_file": "GMAIL-SMTP-SETUP.md", "source_location": "L123"}, {"id": "torus_implementation_gmail_smtp_setup_2_update_env", "label": "**2. Update .env**", "file_type": "document", "source_file": "GMAIL-SMTP-SETUP.md", "source_location": "L130"}, {"id": "torus_implementation_gmail_smtp_setup_3_restart_server", "label": "**3. Restart Server**", "file_type": "document", "source_file": "GMAIL-SMTP-SETUP.md", "source_location": "L136"}, {"id": "torus_implementation_gmail_smtp_setup_4_send_otp", "label": "**4. Send OTP**", "file_type": "document", "source_file": "GMAIL-SMTP-SETUP.md", "source_location": "L141"}, {"id": "torus_implementation_gmail_smtp_setup_complete_otp_flow_updated", "label": "\ud83d\udd22 Complete OTP Flow (Updated)", "file_type": "document", "source_file": "GMAIL-SMTP-SETUP.md", "source_location": "L152"}, {"id": "torus_implementation_gmail_smtp_setup_security_maintained", "label": "\ud83d\udd10 Security Maintained", "file_type": "document", "source_file": "GMAIL-SMTP-SETUP.md", "source_location": "L183"}, {"id": "torus_implementation_gmail_smtp_setup_important_notes", "label": "\u26a0\ufe0f Important Notes", "file_type": "document", "source_file": "GMAIL-SMTP-SETUP.md", "source_location": "L198"}, {"id": "torus_implementation_gmail_smtp_setup_1_app_password_only", "label": "**1. App Password Only**", "file_type": "document", "source_file": "GMAIL-SMTP-SETUP.md", "source_location": "L200"}, {"id": "torus_implementation_gmail_smtp_setup_2_2_step_verification", "label": "**2. 2-Step Verification**", "file_type": "document", "source_file": "GMAIL-SMTP-SETUP.md", "source_location": "L205"}, {"id": "torus_implementation_gmail_smtp_setup_3_no_spaces", "label": "**3. No Spaces**", "file_type": "document", "source_file": "GMAIL-SMTP-SETUP.md", "source_location": "L208"}, {"id": "torus_implementation_gmail_smtp_setup_4_restart_after_env_change", "label": "**4. Restart After .env Change**", "file_type": "document", "source_file": "GMAIL-SMTP-SETUP.md", "source_location": "L212"}, {"id": "torus_implementation_gmail_smtp_setup_email_template_html", "label": "\ud83d\udccb Email Template (HTML)", "file_type": "document", "source_file": "GMAIL-SMTP-SETUP.md", "source_location": "L218"}, {"id": "torus_implementation_gmail_smtp_setup_performance_comparison", "label": "\ud83d\ude80 Performance Comparison", "file_type": "document", "source_file": "GMAIL-SMTP-SETUP.md", "source_location": "L238"}, {"id": "torus_implementation_gmail_smtp_setup_summary", "label": "\ud83c\udfaf Summary", "file_type": "document", "source_file": "GMAIL-SMTP-SETUP.md", "source_location": "L251"}, {"id": "torus_implementation_gmail_smtp_setup_benefits_of_gmail_smtp", "label": "**Benefits of Gmail SMTP**", "file_type": "document", "source_file": "GMAIL-SMTP-SETUP.md", "source_location": "L253"}, {"id": "torus_implementation_gmail_smtp_setup_how_it_works", "label": "**How It Works**", "file_type": "document", "source_file": "GMAIL-SMTP-SETUP.md", "source_location": "L262"}, {"id": "torus_implementation_gmail_smtp_setup_current_status", "label": "\ud83d\udcca Current Status", "file_type": "document", "source_file": "GMAIL-SMTP-SETUP.md", "source_location": "L272"}, {"id": "torus_implementation_gmail_smtp_setup_server_startup_output", "label": "\ud83d\udd27 Server Startup Output", "file_type": "document", "source_file": "GMAIL-SMTP-SETUP.md", "source_location": "L282"}, {"id": "torus_implementation_gmail_smtp_setup_next_steps", "label": "\ud83d\udcde Next Steps", "file_type": "document", "source_file": "GMAIL-SMTP-SETUP.md", "source_location": "L299"}, {"id": "torus_implementation_gmail_smtp_setup_verification_checklist", "label": "\u2705 Verification Checklist", "file_type": "document", "source_file": "GMAIL-SMTP-SETUP.md", "source_location": "L324"}, {"id": "torus_implementation_gmail_smtp_setup_result", "label": "\ud83c\udf89 Result", "file_type": "document", "source_file": "GMAIL-SMTP-SETUP.md", "source_location": "L340"}], "edges": [{"source": "d_torus_implementation_project_torus_implementation_torus_implementation_gmail_smtp_setup_md", "target": "torus_implementation_gmail_smtp_setup_gmail_smtp_otp_system_successfully_configured", "relation": "contains", "confidence": "EXTRACTED", "source_file": "GMAIL-SMTP-SETUP.md", "source_location": "L1", "weight": 1.0}, {"source": "torus_implementation_gmail_smtp_setup_gmail_smtp_otp_system_successfully_configured", "target": "torus_implementation_gmail_smtp_setup_status_fully_operational", "relation": "contains", "confidence": "EXTRACTED", "source_file": "GMAIL-SMTP-SETUP.md", "source_location": "L3", "weight": 1.0}, {"source": "torus_implementation_gmail_smtp_setup_gmail_smtp_otp_system_successfully_configured", "target": "torus_implementation_gmail_smtp_setup_what_changed", "relation": "contains", "confidence": "EXTRACTED", "source_file": "GMAIL-SMTP-SETUP.md", "source_location": "L11", "weight": 1.0}, {"source": "torus_implementation_gmail_smtp_setup_what_changed", "target": "torus_implementation_gmail_smtp_setup_from_resend_api", "relation": "contains", "confidence": "EXTRACTED", "source_file": "GMAIL-SMTP-SETUP.md", "source_location": "L13", "weight": 1.0}, {"source": "torus_implementation_gmail_smtp_setup_what_changed", "target": "torus_implementation_gmail_smtp_setup_to_gmail_smtp_nodemailer", "relation": "contains", "confidence": "EXTRACTED", "source_file": "GMAIL-SMTP-SETUP.md", "source_location": "L21", "weight": 1.0}, {"source": "torus_implementation_gmail_smtp_setup_gmail_smtp_otp_system_successfully_configured", "target": "torus_implementation_gmail_smtp_setup_configuration", "relation": "contains", "confidence": "EXTRACTED", "source_file": "GMAIL-SMTP-SETUP.md", "source_location": "L31", "weight": 1.0}, {"source": "torus_implementation_gmail_smtp_setup_configuration", "target": "torus_implementation_gmail_smtp_setup_installed_dependency", "relation": "contains", "confidence": "EXTRACTED", "source_file": "GMAIL-SMTP-SETUP.md", "source_location": "L33", "weight": 1.0}, {"source": "torus_implementation_gmail_smtp_setup_configuration", "target": "torus_implementation_gmail_smtp_setup_updated_env", "relation": "contains", "confidence": "EXTRACTED", "source_file": "GMAIL-SMTP-SETUP.md", "source_location": "L39", "weight": 1.0}, {"source": "torus_implementation_gmail_smtp_setup_configuration", "target": "torus_implementation_gmail_smtp_setup_backend_configuration_server_js", "relation": "contains", "confidence": "EXTRACTED", "source_file": "GMAIL-SMTP-SETUP.md", "source_location": "L49", "weight": 1.0}, {"source": "torus_implementation_gmail_smtp_setup_gmail_smtp_otp_system_successfully_configured", "target": "torus_implementation_gmail_smtp_setup_send_otp_function", "relation": "contains", "confidence": "EXTRACTED", "source_file": "GMAIL-SMTP-SETUP.md", "source_location": "L70", "weight": 1.0}, {"source": "torus_implementation_gmail_smtp_setup_gmail_smtp_otp_system_successfully_configured", "target": "torus_implementation_gmail_smtp_setup_test_results", "relation": "contains", "confidence": "EXTRACTED", "source_file": "GMAIL-SMTP-SETUP.md", "source_location": "L102", "weight": 1.0}, {"source": "torus_implementation_gmail_smtp_setup_test_results", "target": "torus_implementation_gmail_smtp_setup_test_1_otp_sending", "relation": "contains", "confidence": "EXTRACTED", "source_file": "GMAIL-SMTP-SETUP.md", "source_location": "L104", "weight": 1.0}, {"source": "torus_implementation_gmail_smtp_setup_gmail_smtp_otp_system_successfully_configured", "target": "torus_implementation_gmail_smtp_setup_how_to_use", "relation": "contains", "confidence": "EXTRACTED", "source_file": "GMAIL-SMTP-SETUP.md", "source_location": "L121", "weight": 1.0}, {"source": "torus_implementation_gmail_smtp_setup_how_to_use", "target": "torus_implementation_gmail_smtp_setup_1_get_gmail_app_password", "relation": "contains", "confidence": "EXTRACTED", "source_file": "GMAIL-SMTP-SETUP.md", "source_location": "L123", "weight": 1.0}, {"source": "torus_implementation_gmail_smtp_setup_how_to_use", "target": "torus_implementation_gmail_smtp_setup_2_update_env", "relation": "contains", "confidence": "EXTRACTED", "source_file": "GMAIL-SMTP-SETUP.md", "source_location": "L130", "weight": 1.0}, {"source": "torus_implementation_gmail_smtp_setup_how_to_use", "target": "torus_implementation_gmail_smtp_setup_3_restart_server", "relation": "contains", "confidence": "EXTRACTED", "source_file": "GMAIL-SMTP-SETUP.md", "source_location": "L136", "weight": 1.0}, {"source": "torus_implementation_gmail_smtp_setup_how_to_use", "target": "torus_implementation_gmail_smtp_setup_4_send_otp", "relation": "contains", "confidence": "EXTRACTED", "source_file": "GMAIL-SMTP-SETUP.md", "source_location": "L141", "weight": 1.0}, {"source": "torus_implementation_gmail_smtp_setup_gmail_smtp_otp_system_successfully_configured", "target": "torus_implementation_gmail_smtp_setup_complete_otp_flow_updated", "relation": "contains", "confidence": "EXTRACTED", "source_file": "GMAIL-SMTP-SETUP.md", "source_location": "L152", "weight": 1.0}, {"source": "torus_implementation_gmail_smtp_setup_gmail_smtp_otp_system_successfully_configured", "target": "torus_implementation_gmail_smtp_setup_security_maintained", "relation": "contains", "confidence": "EXTRACTED", "source_file": "GMAIL-SMTP-SETUP.md", "source_location": "L183", "weight": 1.0}, {"source": "torus_implementation_gmail_smtp_setup_gmail_smtp_otp_system_successfully_configured", "target": "torus_implementation_gmail_smtp_setup_important_notes", "relation": "contains", "confidence": "EXTRACTED", "source_file": "GMAIL-SMTP-SETUP.md", "source_location": "L198", "weight": 1.0}, {"source": "torus_implementation_gmail_smtp_setup_important_notes", "target": "torus_implementation_gmail_smtp_setup_1_app_password_only", "relation": "contains", "confidence": "EXTRACTED", "source_file": "GMAIL-SMTP-SETUP.md", "source_location": "L200", "weight": 1.0}, {"source": "torus_implementation_gmail_smtp_setup_important_notes", "target": "torus_implementation_gmail_smtp_setup_2_2_step_verification", "relation": "contains", "confidence": "EXTRACTED", "source_file": "GMAIL-SMTP-SETUP.md", "source_location": "L205", "weight": 1.0}, {"source": "torus_implementation_gmail_smtp_setup_important_notes", "target": "torus_implementation_gmail_smtp_setup_3_no_spaces", "relation": "contains", "confidence": "EXTRACTED", "source_file": "GMAIL-SMTP-SETUP.md", "source_location": "L208", "weight": 1.0}, {"source": "torus_implementation_gmail_smtp_setup_important_notes", "target": "torus_implementation_gmail_smtp_setup_4_restart_after_env_change", "relation": "contains", "confidence": "EXTRACTED", "source_file": "GMAIL-SMTP-SETUP.md", "source_location": "L212", "weight": 1.0}, {"source": "torus_implementation_gmail_smtp_setup_gmail_smtp_otp_system_successfully_configured", "target": "torus_implementation_gmail_smtp_setup_email_template_html", "relation": "contains", "confidence": "EXTRACTED", "source_file": "GMAIL-SMTP-SETUP.md", "source_location": "L218", "weight": 1.0}, {"source": "torus_implementation_gmail_smtp_setup_gmail_smtp_otp_system_successfully_configured", "target": "torus_implementation_gmail_smtp_setup_performance_comparison", "relation": "contains", "confidence": "EXTRACTED", "source_file": "GMAIL-SMTP-SETUP.md", "source_location": "L238", "weight": 1.0}, {"source": "torus_implementation_gmail_smtp_setup_gmail_smtp_otp_system_successfully_configured", "target": "torus_implementation_gmail_smtp_setup_summary", "relation": "contains", "confidence": "EXTRACTED", "source_file": "GMAIL-SMTP-SETUP.md", "source_location": "L251", "weight": 1.0}, {"source": "torus_implementation_gmail_smtp_setup_summary", "target": "torus_implementation_gmail_smtp_setup_benefits_of_gmail_smtp", "relation": "contains", "confidence": "EXTRACTED", "source_file": "GMAIL-SMTP-SETUP.md", "source_location": "L253", "weight": 1.0}, {"source": "torus_implementation_gmail_smtp_setup_summary", "target": "torus_implementation_gmail_smtp_setup_how_it_works", "relation": "contains", "confidence": "EXTRACTED", "source_file": "GMAIL-SMTP-SETUP.md", "source_location": "L262", "weight": 1.0}, {"source": "torus_implementation_gmail_smtp_setup_gmail_smtp_otp_system_successfully_configured", "target": "torus_implementation_gmail_smtp_setup_current_status", "relation": "contains", "confidence": "EXTRACTED", "source_file": "GMAIL-SMTP-SETUP.md", "source_location": "L272", "weight": 1.0}, {"source": "torus_implementation_gmail_smtp_setup_gmail_smtp_otp_system_successfully_configured", "target": "torus_implementation_gmail_smtp_setup_server_startup_output", "relation": "contains", "confidence": "EXTRACTED", "source_file": "GMAIL-SMTP-SETUP.md", "source_location": "L282", "weight": 1.0}, {"source": "torus_implementation_gmail_smtp_setup_gmail_smtp_otp_system_successfully_configured", "target": "torus_implementation_gmail_smtp_setup_next_steps", "relation": "contains", "confidence": "EXTRACTED", "source_file": "GMAIL-SMTP-SETUP.md", "source_location": "L299", "weight": 1.0}, {"source": "torus_implementation_gmail_smtp_setup_gmail_smtp_otp_system_successfully_configured", "target": "torus_implementation_gmail_smtp_setup_verification_checklist", "relation": "contains", "confidence": "EXTRACTED", "source_file": "GMAIL-SMTP-SETUP.md", "source_location": "L324", "weight": 1.0}, {"source": "torus_implementation_gmail_smtp_setup_gmail_smtp_otp_system_successfully_configured", "target": "torus_implementation_gmail_smtp_setup_result", "relation": "contains", "confidence": "EXTRACTED", "source_file": "GMAIL-SMTP-SETUP.md", "source_location": "L340", "weight": 1.0}], "input_tokens": 0, "output_tokens": 0}